LICENSE
README.md
setup.cfg
setup.py
commontools/__init__.py
commontools/simple_format.py
commontools/simple_request.py
flow_package_utils.egg-info/PKG-INFO
flow_package_utils.egg-info/SOURCES.txt
flow_package_utils.egg-info/dependency_links.txt
flow_package_utils.egg-info/requires.txt
flow_package_utils.egg-info/top_level.txt